arinc429/__init__.py
arinc429/common.py
arinc429/decoder.py
arinc429/encoder.py
arinc429-0.1.6.dist-info/licenses/LICENSE
arinc429-0.1.6.dist-info/METADATA
arinc429-0.1.6.dist-info/WHEEL
arinc429-0.1.6.dist-info/top_level.txt
arinc429-0.1.6.dist-info/RECORD
