Metadata-Version: 2.4
Name: arinc429
Version: 0.1.6
Summary: A library for working with ARINC 429 data
Home-page: https://github.com/jaimebw/arinc429
Author: Jaime Bowen Varela
Author-email: Jaime Bowen Varela <jaimebwv@gmail.com>
Project-URL: Homepage, https://github.com/jaimebw/arinc429
Project-URL: Issues, https://github.com/jaimebw/arinc429/issues
Classifier: Development Status :: 3 - Alpha
Classifier: Intended Audience :: Developers
Classifier: License :: OSI Approved :: MIT License
Classifier: Programming Language :: Python :: 3
Classifier: Programming Language :: Python :: 3.7
Classifier: Programming Language :: Python :: 3.8
Classifier: Programming Language :: Python :: 3.9
Classifier: Programming Language :: Python :: 3.10
Classifier: Topic :: Software Development :: Libraries :: Python Modules
Classifier: Topic :: Scientific/Engineering :: Interface Engine/Protocol Translator
Requires-Python: >=3.7
License-File: LICENSE
Provides-Extra: dev
Requires-Dist: pytest>=7.0.0; extra == "dev"
Dynamic: author
Dynamic: home-page
Dynamic: license-file
Dynamic: requires-python
